{
  "total": [
    {
      "id": "100031586233995",
      "count": 0
    },
    {
      "id": "100055836891749",
      "count": 0
    },
    {
      "id": "100056790952924",
      "count": 0
    },
    {
      "id": "100036904335886",
      "count": 0
    },
    {
      "id": "100045357438307",
      "count": 0
    },
    {
      "id": "100034186181243",
      "count": 0
    },
    {
      "id": "100052315125888",
      "count": 0
    },
    {
      "id": "100033847366800",
      "count": 27
    },
    {
      "id": "100066569161614",
      "count": 0
    },
    {
      "id": "100053419996916",
      "count": 0
    },
    {
      "id": "100066800292323",
      "count": 0
    },
    {
      "id": "100030441544523",
      "count": 0
    },
    {
      "id": "100086565205526",
      "count": 0
    },
    {
      "id": "100047836389499",
      "count": 0
    },
    {
      "id": "100014079603608",
      "count": 0
    },
    {
      "id": "100087113063162",
      "count": 0
    },
    {
      "id": "100043697130735",
      "count": 0
    },
    {
      "id": "100044240073742",
      "count": 41
    },
    {
      "id": "100044655052464",
      "count": 0
    },
    {
      "id": "100057252901912",
      "count": 7
    },
    {
      "id": "100047944021607",
      "count": 0
    },
    {
      "id": "100023102469370",
      "count": 0
    },
    {
      "id": "100024138003862",
      "count": 0
    },
    {
      "id": "100063641239323",
      "count": 0
    },
    {
      "id": "61573779976705",
      "count": 0
    },
    {
      "id": "100040429782174",
      "count": 0
    },
    {
      "id": "61555280964623",
      "count": 0
    },
    {
      "id": "100095084831973",
      "count": 0
    },
    {
      "id": "100037471119852",
      "count": 0
    },
    {
      "id": "100039900949087",
      "count": 0
    },
    {
      "id": "100029811588017",
      "count": 0
    },
    {
      "id": "100034686153838",
      "count": 0
    },
    {
      "id": "100037851137057",
      "count": 0
    },
    {
      "id": "100056668094331",
      "count": 0
    },
    {
      "id": "100083370035124",
      "count": 0
    },
    {
      "id": "100056926724055",
      "count": 0
    },
    {
      "id": "61554825643578",
      "count": 0
    },
    {
      "id": "100072481492352",
      "count": 0
    },
    {
      "id": "100008525405185",
      "count": 0
    },
    {
      "id": "100032240658344",
      "count": 0
    },
    {
      "id": "100065101000674",
      "count": 0
    },
    {
      "id": "100035581415243",
      "count": 0
    },
    {
      "id": "100012597155947",
      "count": 0
    },
    {
      "id": "100038774804198",
      "count": 0
    },
    {
      "id": "100053014713547",
      "count": 1
    },
    {
      "id": "100034476131469",
      "count": 0
    },
    {
      "id": "61574452195051",
      "count": 0
    },
    {
      "id": "1519741715",
      "count": 0
    },
    {
      "id": "100021630859935",
      "count": 0
    },
    {
      "id": "100094343156847",
      "count": 0
    },
    {
      "id": "100047623698068",
      "count": 0
    },
    {
      "id": "100018593952611",
      "count": 0
    },
    {
      "id": "100036596405786",
      "count": 66
    },
    {
      "id": "100076477178662",
      "count": 0
    },
    {
      "id": "61580977525829",
      "count": 49
    },
    {
      "id": "61562877035114",
      "count": 0
    },
    {
      "id": "100025503051062",
      "count": 0
    },
    {
      "id": "100055271865425",
      "count": 0
    }
  ],
  "month": [
    {
      "id": "100031586233995",
      "count": 0
    },
    {
      "id": "100055836891749",
      "count": 0
    },
    {
      "id": "100056790952924",
      "count": 0
    },
    {
      "id": "100036904335886",
      "count": 0
    },
    {
      "id": "100045357438307",
      "count": 0
    },
    {
      "id": "100034186181243",
      "count": 0
    },
    {
      "id": "100052315125888",
      "count": 0
    },
    {
      "id": "100033847366800",
      "count": 0
    },
    {
      "id": "100066569161614",
      "count": 0
    },
    {
      "id": "100053419996916",
      "count": 0
    },
    {
      "id": "100066800292323",
      "count": 0
    },
    {
      "id": "100030441544523",
      "count": 0
    },
    {
      "id": "100086565205526",
      "count": 0
    },
    {
      "id": "100047836389499",
      "count": 0
    },
    {
      "id": "100014079603608",
      "count": 0
    },
    {
      "id": "100087113063162",
      "count": 0
    },
    {
      "id": "100043697130735",
      "count": 0
    },
    {
      "id": "100044240073742",
      "count": 0
    },
    {
      "id": "100044655052464",
      "count": 0
    },
    {
      "id": "100057252901912",
      "count": 0
    },
    {
      "id": "100047944021607",
      "count": 0
    },
    {
      "id": "100023102469370",
      "count": 0
    },
    {
      "id": "100024138003862",
      "count": 0
    },
    {
      "id": "100063641239323",
      "count": 0
    },
    {
      "id": "61573779976705",
      "count": 0
    },
    {
      "id": "100040429782174",
      "count": 0
    },
    {
      "id": "61555280964623",
      "count": 0
    },
    {
      "id": "100095084831973",
      "count": 0
    },
    {
      "id": "100037471119852",
      "count": 0
    },
    {
      "id": "100039900949087",
      "count": 0
    },
    {
      "id": "100029811588017",
      "count": 0
    },
    {
      "id": "100034686153838",
      "count": 0
    },
    {
      "id": "100037851137057",
      "count": 0
    },
    {
      "id": "100056668094331",
      "count": 0
    },
    {
      "id": "100083370035124",
      "count": 0
    },
    {
      "id": "100056926724055",
      "count": 0
    },
    {
      "id": "61554825643578",
      "count": 0
    },
    {
      "id": "100072481492352",
      "count": 0
    },
    {
      "id": "100008525405185",
      "count": 0
    },
    {
      "id": "100032240658344",
      "count": 0
    },
    {
      "id": "100065101000674",
      "count": 0
    },
    {
      "id": "100035581415243",
      "count": 0
    },
    {
      "id": "100012597155947",
      "count": 0
    },
    {
      "id": "100038774804198",
      "count": 0
    },
    {
      "id": "100053014713547",
      "count": 0
    },
    {
      "id": "100034476131469",
      "count": 0
    },
    {
      "id": "61574452195051",
      "count": 0
    },
    {
      "id": "1519741715",
      "count": 0
    },
    {
      "id": "100021630859935",
      "count": 0
    },
    {
      "id": "100094343156847",
      "count": 0
    },
    {
      "id": "100047623698068",
      "count": 0
    },
    {
      "id": "100018593952611",
      "count": 0
    },
    {
      "id": "100036596405786",
      "count": 0
    },
    {
      "id": "100076477178662",
      "count": 0
    },
    {
      "id": "61580977525829",
      "count": 0
    },
    {
      "id": "61562877035114",
      "count": 0
    },
    {
      "id": "100025503051062",
      "count": 0
    },
    {
      "id": "100055271865425",
      "count": 0
    }
  ],
  "week": [
    {
      "id": "100031586233995",
      "count": 0
    },
    {
      "id": "100055836891749",
      "count": 0
    },
    {
      "id": "100056790952924",
      "count": 0
    },
    {
      "id": "100036904335886",
      "count": 0
    },
    {
      "id": "100045357438307",
      "count": 0
    },
    {
      "id": "100034186181243",
      "count": 0
    },
    {
      "id": "100052315125888",
      "count": 0
    },
    {
      "id": "100033847366800",
      "count": 0
    },
    {
      "id": "100066569161614",
      "count": 0
    },
    {
      "id": "100053419996916",
      "count": 0
    },
    {
      "id": "100066800292323",
      "count": 0
    },
    {
      "id": "100030441544523",
      "count": 0
    },
    {
      "id": "100086565205526",
      "count": 0
    },
    {
      "id": "100047836389499",
      "count": 0
    },
    {
      "id": "100014079603608",
      "count": 0
    },
    {
      "id": "100087113063162",
      "count": 0
    },
    {
      "id": "100043697130735",
      "count": 0
    },
    {
      "id": "100044240073742",
      "count": 0
    },
    {
      "id": "100044655052464",
      "count": 0
    },
    {
      "id": "100057252901912",
      "count": 0
    },
    {
      "id": "100047944021607",
      "count": 0
    },
    {
      "id": "100023102469370",
      "count": 0
    },
    {
      "id": "100024138003862",
      "count": 0
    },
    {
      "id": "100063641239323",
      "count": 0
    },
    {
      "id": "61573779976705",
      "count": 0
    },
    {
      "id": "100040429782174",
      "count": 0
    },
    {
      "id": "61555280964623",
      "count": 0
    },
    {
      "id": "100095084831973",
      "count": 0
    },
    {
      "id": "100037471119852",
      "count": 0
    },
    {
      "id": "100039900949087",
      "count": 0
    },
    {
      "id": "100029811588017",
      "count": 0
    },
    {
      "id": "100034686153838",
      "count": 0
    },
    {
      "id": "100037851137057",
      "count": 0
    },
    {
      "id": "100056668094331",
      "count": 0
    },
    {
      "id": "100083370035124",
      "count": 0
    },
    {
      "id": "100056926724055",
      "count": 0
    },
    {
      "id": "61554825643578",
      "count": 0
    },
    {
      "id": "100072481492352",
      "count": 0
    },
    {
      "id": "100008525405185",
      "count": 0
    },
    {
      "id": "100032240658344",
      "count": 0
    },
    {
      "id": "100065101000674",
      "count": 0
    },
    {
      "id": "100035581415243",
      "count": 0
    },
    {
      "id": "100012597155947",
      "count": 0
    },
    {
      "id": "100038774804198",
      "count": 0
    },
    {
      "id": "100053014713547",
      "count": 0
    },
    {
      "id": "100034476131469",
      "count": 0
    },
    {
      "id": "61574452195051",
      "count": 0
    },
    {
      "id": "1519741715",
      "count": 0
    },
    {
      "id": "100021630859935",
      "count": 0
    },
    {
      "id": "100094343156847",
      "count": 0
    },
    {
      "id": "100047623698068",
      "count": 0
    },
    {
      "id": "100018593952611",
      "count": 0
    },
    {
      "id": "100036596405786",
      "count": 0
    },
    {
      "id": "100076477178662",
      "count": 0
    },
    {
      "id": "61580977525829",
      "count": 0
    },
    {
      "id": "61562877035114",
      "count": 0
    },
    {
      "id": "100025503051062",
      "count": 0
    },
    {
      "id": "100055271865425",
      "count": 0
    }
  ],
  "day": [
    {
      "id": "100031586233995",
      "count": 0
    },
    {
      "id": "100055836891749",
      "count": 0
    },
    {
      "id": "100056790952924",
      "count": 0
    },
    {
      "id": "100036904335886",
      "count": 0
    },
    {
      "id": "100045357438307",
      "count": 0
    },
    {
      "id": "100034186181243",
      "count": 0
    },
    {
      "id": "100052315125888",
      "count": 0
    },
    {
      "id": "100033847366800",
      "count": 0
    },
    {
      "id": "100066569161614",
      "count": 0
    },
    {
      "id": "100053419996916",
      "count": 0
    },
    {
      "id": "100066800292323",
      "count": 0
    },
    {
      "id": "100030441544523",
      "count": 0
    },
    {
      "id": "100086565205526",
      "count": 0
    },
    {
      "id": "100047836389499",
      "count": 0
    },
    {
      "id": "100014079603608",
      "count": 0
    },
    {
      "id": "100087113063162",
      "count": 0
    },
    {
      "id": "100043697130735",
      "count": 0
    },
    {
      "id": "100044240073742",
      "count": 0
    },
    {
      "id": "100044655052464",
      "count": 0
    },
    {
      "id": "100057252901912",
      "count": 0
    },
    {
      "id": "100047944021607",
      "count": 0
    },
    {
      "id": "100023102469370",
      "count": 0
    },
    {
      "id": "100024138003862",
      "count": 0
    },
    {
      "id": "100063641239323",
      "count": 0
    },
    {
      "id": "61573779976705",
      "count": 0
    },
    {
      "id": "100040429782174",
      "count": 0
    },
    {
      "id": "61555280964623",
      "count": 0
    },
    {
      "id": "100095084831973",
      "count": 0
    },
    {
      "id": "100037471119852",
      "count": 0
    },
    {
      "id": "100039900949087",
      "count": 0
    },
    {
      "id": "100029811588017",
      "count": 0
    },
    {
      "id": "100034686153838",
      "count": 0
    },
    {
      "id": "100037851137057",
      "count": 0
    },
    {
      "id": "100056668094331",
      "count": 0
    },
    {
      "id": "100083370035124",
      "count": 0
    },
    {
      "id": "100056926724055",
      "count": 0
    },
    {
      "id": "61554825643578",
      "count": 0
    },
    {
      "id": "100072481492352",
      "count": 0
    },
    {
      "id": "100008525405185",
      "count": 0
    },
    {
      "id": "100032240658344",
      "count": 0
    },
    {
      "id": "100065101000674",
      "count": 0
    },
    {
      "id": "100035581415243",
      "count": 0
    },
    {
      "id": "100012597155947",
      "count": 0
    },
    {
      "id": "100038774804198",
      "count": 0
    },
    {
      "id": "100053014713547",
      "count": 0
    },
    {
      "id": "100034476131469",
      "count": 0
    },
    {
      "id": "61574452195051",
      "count": 0
    },
    {
      "id": "1519741715",
      "count": 0
    },
    {
      "id": "100021630859935",
      "count": 0
    },
    {
      "id": "100094343156847",
      "count": 0
    },
    {
      "id": "100047623698068",
      "count": 0
    },
    {
      "id": "100018593952611",
      "count": 0
    },
    {
      "id": "100036596405786",
      "count": 0
    },
    {
      "id": "100076477178662",
      "count": 0
    },
    {
      "id": "61580977525829",
      "count": 0
    },
    {
      "id": "61562877035114",
      "count": 0
    },
    {
      "id": "100025503051062",
      "count": 0
    },
    {
      "id": "100055271865425",
      "count": 0
    }
  ],
  "lastDay": 4,
  "lastWeek": 23,
  "lastMonth": 5
}